cae_model/__init__.py
cae_model/element_types.py
cae_model/fc.py
cae_model/vtu.py
cae_model-0.0.1.dist-info/LICENSE
cae_model-0.0.1.dist-info/METADATA
cae_model-0.0.1.dist-info/WHEEL
cae_model-0.0.1.dist-info/top_level.txt
cae_model-0.0.1.dist-info/RECORD
